functional_tests/__init__.py
functional_tests/test_validator.py
validator/chromemanifest.py
validator/compat.py
validator/constants.py
validator/contextgenerator.py
validator/decorator.py
validator/errorbundler.py
validator/json_parser.py
validator/loader.py
validator/main.py
validator/metadata_helpers.py
validator/opensearch.py
validator/rdf.py
validator/submain.py
validator/typedetection.py
validator/unicodehelper.py
validator/validate.py
validator/version.py
validator/xpi.py
validator/app_versions.json
validator/__init__.py
validator/outputhandlers/__init__.py
validator/outputhandlers/shellcolors.py
validator/python/HTMLParser.py
validator/python/__init__.py
validator/testcases/__init__.py
validator/testcases/chromemanifest.py
validator/testcases/content.py
validator/testcases/installrdf.py
validator/testcases/jetpack.py
validator/testcases/l10ncompleteness.py
validator/testcases/langpack.py
validator/testcases/packagelayout.py
validator/testcases/regex.py
validator/testcases/scripting.py
validator/testcases/targetapplication.py
validator/testcases/themes.py
validator/testcases/hashes-allowed.txt
validator/testcases/hashes-error.txt
validator/testcases/hashes-warning.txt
validator/testcases/jetpack_data.txt
validator/testcases/jetpack_data.txt.pickle
validator/testcases/static_hashes.txt
validator/testcases/javascript/__init__.py
validator/testcases/javascript/actions.py
validator/testcases/javascript/call_definitions.py
validator/testcases/javascript/entity_values.py
validator/testcases/javascript/instanceactions.py
validator/testcases/javascript/instanceproperties.py
validator/testcases/javascript/jstypes.py
validator/testcases/javascript/nodedefinitions.py
validator/testcases/javascript/predefinedentities.py
validator/testcases/javascript/traverser.py
validator/testcases/javascript/jsshell.py
validator/testcases/l10n/__init__.py
validator/testcases/l10n/dtd.py
validator/testcases/l10n/properties.py
amo_validator-1.11.2.dist-info/top_level.txt
amo_validator-1.11.2.dist-info/METADATA
amo_validator-1.11.2.dist-info/DESCRIPTION.rst
amo_validator-1.11.2.dist-info/metadata.json
amo_validator-1.11.2.dist-info/WHEEL
amo_validator-1.11.2.dist-info/RECORD
