Metadata-Version: 2.0
Name: amo-validator
Version: 1.11.2
Summary: Validates add-ons for Mozilla products.
Home-page: http://github.com/mozilla/amo-validator
Author: Matt Basta
Author-email: me@mattbasta.com
License: BSD
Platform: UNKNOWN
Classifier: Development Status :: 7 - Inactive
Classifier: Environment :: Web Environment
Classifier: Intended Audience :: Developers
Classifier: License :: OSI Approved :: BSD License
Classifier: Operating System :: OS Independent
Classifier: Programming Language :: Python
Classifier: Topic :: Software Development :: Libraries :: Python Modules
Requires-Dist: argparse (==1.4.0)
Requires-Dist: cssutils (==1.0.2)
Requires-Dist: defusedxml (==0.5.0)
Requires-Dist: fastchardet (==0.2.0)
Requires-Dist: mock (==2.0.0)
Requires-Dist: natsort (==5.3.3)
Requires-Dist: pytest (==3.7.1)
Requires-Dist: rdflib (==3.4.0)
Requires-Dist: requests (==2.19.1)
Requires-Dist: simplejson (==3.16.0)
Requires-Dist: spidermonkey (==58.0a1.post2)
